pyeccodes
