Metadata-Version: 2.1
Name: pyeccodes
Version: 0.1.1
Summary: Experimental pure Python version of eccodes
Home-page: https://github.com/b8raoult/pyeccodes
Author: ECMWF
Author-email: software.support@ecmwf.int
License: Apache 2.0
Platform: UNKNOWN
Classifier: Development Status :: 3 - Alpha
Classifier: Intended Audience :: Developers
Classifier: Programming Language :: Python
Classifier: Programming Language :: Python :: 3
Classifier: Programming Language :: Python :: 3.4
Classifier: Programming Language :: Python :: 3.5
Classifier: Programming Language :: Python :: 3.6
Classifier: Programming Language :: Python :: Implementation :: CPython
Classifier: Programming Language :: Python :: Implementation :: PyPy
Classifier: Operating System :: OS Independent
